topi/__init__.py
topi/exceptions.py
topi/item.py
topi/record.py
topi/tind.py
topi/tind_utils.py
topi-1.1.0.dist-info/LICENSE
topi-1.1.0.dist-info/METADATA
topi-1.1.0.dist-info/WHEEL
topi-1.1.0.dist-info/top_level.txt
topi-1.1.0.dist-info/RECORD
