Metadata-Version: 2.1
Name: topi
Version: 1.1.0
Summary: A Python package for getting basic data from a TIND.io server
Home-page: https://github.com/caltechlibrary/topi
Author: Michael Hucka
Author-email: mhucka@caltech.edu
License: BSD 3-clause
Project-URL: Source Code, https://github.com/caltechlibrary/topi
Project-URL: Bug Tracker, https://github.com/caltechlibrary/topi/issues
Keywords: Python,utilities
Platform: UNKNOWN
Classifier: Development Status :: 4 - Beta
Classifier: Intended Audience :: Science/Research
Classifier: License :: OSI Approved :: BSD License
Classifier: Operating System :: MacOS :: MacOS X
Classifier: Operating System :: Microsoft :: Windows
Classifier: Operating System :: POSIX
Classifier: Operating System :: POSIX :: Linux
Classifier: Operating System :: Unix
Classifier: Programming Language :: Python
Classifier: Programming Language :: Python :: 3.8
Requires-Python: >=3.8
License-File: LICENSE
Requires-Dist: commonpy (>=1.0.0)
Requires-Dist: cssselect (>=1.1.0)
Requires-Dist: lxml (>=4.6.2)
Requires-Dist: sidetrack (>=1.4.0)
